{
  "customer_id": "park_younghee_75",
  "name": "박영희",
  "age": 75,
  "gender": "F",
  "profile": {
    "investment_propensity_self_reported": "적극투자형",
    "high_risk_product_history_5y": [],
    "recent_large_expenses_3m": [
      {"category": "의료비", "amount_krw": 12000000, "month": "2026-04"}
    ],
    "monthly_avg_transfer_krw": 300000,
    "registered_devices": ["갤럭시 S22", "iPad 9"],
    "accessibility_flags": ["senior_mode_eligible"]
  },
  "recent_activity": {
    "incoming_calls_last_24h": [
      {"number": "010-0000-XXXX", "duration_sec": 1450, "claimed_identity": "손주"}
    ],
    "call_history_with_alleged_grandson_6m": [],
    "registered_emergency_contacts": [
      {"name": "박철수 (아들)", "phone": "010-1111-XXXX"},
      {"name": "박지민 (실제 손주)", "phone": "010-2222-XXXX"}
    ]
  }
}
